r2x_plexos/__init__.py
r2x_plexos/config/defaults.json
r2x_plexos/config/file_mapping.json
r2x_plexos/config/master_9.2R6_btu.xml
r2x_plexos/config.py
r2x_plexos/datafile_handler.py
r2x_plexos/exporter.py
r2x_plexos/models/__init__.py
r2x_plexos/models/base.py
r2x_plexos/models/battery.py
r2x_plexos/models/collection_property.py
r2x_plexos/models/component.py
r2x_plexos/models/context.py
r2x_plexos/models/datafile.py
r2x_plexos/models/fuel.py
r2x_plexos/models/generator.py
r2x_plexos/models/interface.py
r2x_plexos/models/line.py
r2x_plexos/models/membership.py
r2x_plexos/models/model.py
r2x_plexos/models/node.py
r2x_plexos/models/property.py
r2x_plexos/models/property_specification.py
r2x_plexos/models/py.typed
r2x_plexos/models/region.py
r2x_plexos/models/registry.py
r2x_plexos/models/reserve.py
r2x_plexos/models/scenario.py
r2x_plexos/models/simulation_config.py
r2x_plexos/models/storage.py
r2x_plexos/models/timeslice.py
r2x_plexos/models/transformers.py
r2x_plexos/models/utils.py
r2x_plexos/models/variable.py
r2x_plexos/models/zone.py
r2x_plexos/parser.py
r2x_plexos/plugins.py
r2x_plexos/py.typed
r2x_plexos/sql/scenario_read_order.sql
r2x_plexos/utils_exporter.py
r2x_plexos/utils_mappings.py
r2x_plexos/utils_parser.py
r2x_plexos/utils_plexosdb.py
r2x_plexos/utils_simulation.py
r2x_plexos-0.1.3.dist-info/WHEEL
r2x_plexos-0.1.3.dist-info/entry_points.txt
r2x_plexos-0.1.3.dist-info/METADATA
r2x_plexos-0.1.3.dist-info/RECORD
