Metadata-Version: 2.3
Name: r2x-plexos
Version: 0.1.3
Summary: Plexos Models, Parser and Exporter
Keywords: PLEXOS
Classifier: Development Status :: 4 - Beta
Classifier: Intended Audience :: Developers
Classifier: Intended Audience :: Science/Research
Classifier: License :: OSI Approved :: BSD License
Classifier: Topic :: Software Development :: Build Tools
Classifier: Programming Language :: Python
Classifier: Programming Language :: Python :: 3
Classifier: Programming Language :: Python :: 3 :: Only
Classifier: Programming Language :: Python :: 3.11
Classifier: Programming Language :: Python :: 3.12
Classifier: Programming Language :: Python :: 3.13
Classifier: License :: OSI Approved :: BSD License
Classifier: Natural Language :: English
Classifier: Operating System :: OS Independent
Classifier: Topic :: File Formats :: JSON
Classifier: Topic :: Scientific/Engineering
Classifier: Topic :: Scientific/Engineering :: Information Analysis
Classifier: Topic :: Scientific/Engineering :: Interface Engine/Protocol Translator
Classifier: Topic :: Software Development :: Build Tools
Classifier: Topic :: Software Development :: Libraries :: Python Modules
Classifier: Typing :: Typed
Requires-Dist: plexosdb>=1.3.0
Requires-Dist: r2x-core>=0.2.1,<1.0.0
Requires-Python: >=3.11, <3.14
Project-URL: Changelog, https://nrel.github.io/r2x-plexos/CHANGELOG.html
Project-URL: Documentation, https://nrel.github.io/r2x-plexos/
Project-URL: Homepage, https://github.com/NREL/r2x-plexos
Project-URL: Issues, https://github.com/NREL/r2x-plexos/issues
Project-URL: Repository, https://github.com/NREL/r2x-plexos
